odoo10_addon_shopinvader_product_stock-10.0.1.0.1.99.dev10-py3.8-nspkg.pth
odoo/addons/shopinvader_product_stock/README.rst
odoo/addons/shopinvader_product_stock/__init__.py
odoo/addons/shopinvader_product_stock/__manifest__.py
odoo/addons/shopinvader_product_stock/hooks.py
odoo/addons/shopinvader_product_stock/data/ir_export_product.xml
odoo/addons/shopinvader_product_stock/i18n/shopinvader_product_stock.pot
odoo/addons/shopinvader_product_stock/models/__init__.py
odoo/addons/shopinvader_product_stock/models/product_product.py
odoo/addons/shopinvader_product_stock/models/shopinvader_backend.py
odoo/addons/shopinvader_product_stock/models/shopinvader_variant.py
odoo/addons/shopinvader_product_stock/models/stock_move.py
odoo/addons/shopinvader_product_stock/tests/__init__.py
odoo/addons/shopinvader_product_stock/tests/common.py
odoo/addons/shopinvader_product_stock/tests/test_product.py
odoo/addons/shopinvader_product_stock/tests/test_stock_move.py
odoo/addons/shopinvader_product_stock/views/shopinvader_backend.xml
odoo10_addon_shopinvader_product_stock-10.0.1.0.1.99.dev10.dist-info/METADATA
odoo10_addon_shopinvader_product_stock-10.0.1.0.1.99.dev10.dist-info/WHEEL
odoo10_addon_shopinvader_product_stock-10.0.1.0.1.99.dev10.dist-info/namespace_packages.txt
odoo10_addon_shopinvader_product_stock-10.0.1.0.1.99.dev10.dist-info/top_level.txt
odoo10_addon_shopinvader_product_stock-10.0.1.0.1.99.dev10.dist-info/RECORD
