Metadata-Version: 2.1
Name: odoo10-addon-shopinvader-product-stock
Version: 10.0.1.0.1.99.dev10
Summary: This module is used to choose a stock field during theexport (by backend)
Home-page: https://github.com/shopinvader/odoo-shopinvader
Author: Akretion,ACSONE SA/NV
License: AGPL-3
Platform: UNKNOWN
Classifier: Programming Language :: Python
Classifier: Framework :: Odoo
Classifier: License :: OSI Approved :: GNU Affero General Public License v3
Requires-Python: ~=2.7
Requires-Dist: odoo10-addon-connector-search-engine
Requires-Dist: odoo10-addon-queue-job
Requires-Dist: odoo10-addon-shopinvader
Requires-Dist: odoo10-addon-shopinvader-search-engine
Requires-Dist: odoo (<10.1dev,>=10.0)
Requires-Dist: openupgradelib
Requires-Dist: slugify
